GPL-2.0
HISTORY
INSTALL
MANIFEST.in
README.md
_mysql.c
_mysql_exceptions.py
metadata.cfg
pymemcompat.h
setup.cfg
setup.py
setup_common.py
setup_posix.py
setup_windows.py
site.cfg
MySQL_python_glb.egg-info/PKG-INFO
MySQL_python_glb.egg-info/SOURCES.txt
MySQL_python_glb.egg-info/dependency_links.txt
MySQL_python_glb.egg-info/top_level.txt
MySQLdb/__init__.py
MySQLdb/connections.py
MySQLdb/converters.py
MySQLdb/cursors.py
MySQLdb/release.py
MySQLdb/times.py
MySQLdb/constants/CLIENT.py
MySQLdb/constants/CR.py
MySQLdb/constants/ER.py
MySQLdb/constants/FIELD_TYPE.py
MySQLdb/constants/FLAG.py
MySQLdb/constants/REFRESH.py
MySQLdb/constants/__init__.py
doc/FAQ.rst
doc/MySQLdb.constants.rst
doc/MySQLdb.rst
doc/_mysql.rst
doc/_mysql_exceptions.rst
doc/conf.py
doc/index.rst
doc/modules.rst
doc/user_guide.rst
tests/capabilities.py
tests/configdb.py
tests/dbapi20.py
tests/test_MySQLdb_capabilities.py
tests/test_MySQLdb_dbapi20.py
tests/test_MySQLdb_nonstandard.py